Metadata-Version: 2.4
Name: the_well
Version: 1.1.0
Summary: A large-scale collection of machine learning datasets of various spatiotemporal physical systems
Author: Miles Cranmer, Michael McCabe, Lucas Meyer, Rudy Morel, Ruben Ohana, Bruno Régaldo-Saint Blancard, François Rozet
Maintainer: Miles Cranmer, Mike McCabe, Lucas Meyer, Payel Mukhopadhyay, Ruben Ohana, François Rozet
License: BSD 3-Clause License
Project-URL: documentation, https://polymathic-ai.org/the_well
Project-URL: organization, https://polymathic-ai.org/
Project-URL: source, https://github.com/PolymathicAI/the_well
Project-URL: tracker, https://github.com/PolymathicAI/the_well/issues
Classifier: Development Status :: 5 - Production/Stable
Classifier: Intended Audience :: Science/Research
Classifier: License :: OSI Approved :: BSD License
Classifier: Operating System :: OS Independent
Classifier: Programming Language :: Python :: 3.10
Classifier: Programming Language :: Python :: 3.11
Classifier: Programming Language :: Python :: 3.12
Classifier: Programming Language :: Python :: 3.13
Classifier: Topic :: Scientific/Engineering :: Artificial Intelligence
Classifier: Topic :: Scientific/Engineering :: Physics
Requires-Python: >=3.10
License-File: LICENSE
Requires-Dist: einops>=0.8
Requires-Dist: h5py>=3.9.0
Requires-Dist: numpy>=1.20
Requires-Dist: pyyaml>=6.0
Requires-Dist: torch>=2.1
Provides-Extra: benchmark
Requires-Dist: hydra-core<2,>=1.3; extra == "benchmark"
Requires-Dist: matplotlib<4,>=3.8; extra == "benchmark"
Requires-Dist: neuraloperator==0.3.0; extra == "benchmark"
Requires-Dist: omegaconf<3,>=2.0; extra == "benchmark"
Requires-Dist: plotly<6,>=5.0; extra == "benchmark"
Requires-Dist: timm<2,>=1.0; extra == "benchmark"
Requires-Dist: torch_harmonics<0.7,>=0.6; extra == "benchmark"
Requires-Dist: wandb<0.18,>=0.17.9; extra == "benchmark"
Requires-Dist: torchinfo<2,>=1.8.0; extra == "benchmark"
Requires-Dist: huggingface-hub; extra == "benchmark"
Provides-Extra: dev
Requires-Dist: pre-commit; extra == "dev"
Requires-Dist: pytest; extra == "dev"
Requires-Dist: pytest-order; extra == "dev"
Requires-Dist: ruff; extra == "dev"
Provides-Extra: docs
Requires-Dist: mkdocs==1.6.1; extra == "docs"
Requires-Dist: mkdocs-jupyter==0.25.1; extra == "docs"
Requires-Dist: mkdocs-material==9.5.45; extra == "docs"
Requires-Dist: mkdocstrings-python==1.12.2; extra == "docs"
Dynamic: license-file
